peer_review_agent/__init__.py
peer_review_agent/cli.py
peer_review_agent/orchestrator.py
peer_review_agent-0.1.0.dist-info/METADATA
peer_review_agent-0.1.0.dist-info/WHEEL
peer_review_agent-0.1.0.dist-info/entry_points.txt
peer_review_agent-0.1.0.dist-info/top_level.txt
peer_review_agent-0.1.0.dist-info/RECORD
