Metadata-Version: 2.4
Name: peer-review-agent
Version: 0.1.0
Summary: Automated peer-review toolkit that extracts text, analyzes quality, and generates review artifacts.
Author: Automated Peer Review Team
Keywords: peer-review,journal club,automation,python,cli
Classifier: License :: OSI Approved :: MIT License
Classifier: Programming Language :: Python :: 3
Classifier: Programming Language :: Python :: 3.9
Classifier: Programming Language :: Python :: 3.10
Classifier: Programming Language :: Python :: 3.11
Classifier: Programming Language :: Python :: 3.12
Classifier: Intended Audience :: Science/Research
Classifier: Topic :: Scientific/Engineering
Classifier: Topic :: Utilities
Requires-Python: >=3.9
Requires-Dist: PyPDF2>=3.0.1
Requires-Dist: python-pptx>=0.6.21
Requires-Dist: python-docx>=1.1.0
Provides-Extra: dev
Requires-Dist: pytest>=8.0.0; extra == "dev"
Requires-Dist: ruff>=0.6.0; extra == "dev"
